[
  {
    "uid": "68785561-a9ca-42b0-be39-cd20ca4ef0c3",
    "firstname": "Gabi",
    "lastname": "Klammt",
    "username": "gklammt0"
  },
  {
    "uid": "0e056e52-5c33-480f-9174-f90cf03b0d61",
    "firstname": "Gram",
    "lastname": "Lammin",
    "username": "glammin1"
  },
  {
    "uid": "a5398c16-080c-4204-8f3c-093f92f7b29c",
    "firstname": "Lucio",
    "lastname": "Barthot",
    "username": "lbarthot2"
  },
  {
    "uid": "7d0c7ae3-dc03-4caf-8d13-8a8244d0c922",
    "firstname": "Selig",
    "lastname": "Gillam",
    "username": "sgillam3"
  },
  {
    "uid": "5523c263-8174-4cae-9da3-1e0bab9fe6d2",
    "firstname": "Lon",
    "lastname": "MacDearmaid",
    "username": "lmacdearmaid4"
  },
  {
    "uid": "8c1cb6f3-caed-4c8e-abd2-f4d453e2d0e7",
    "firstname": "Moses",
    "lastname": "Moggan",
    "username": "mmoggan5"
  },
  {
    "uid": "f8f470ab-22b0-4a32-8102-aac06cac27f3",
    "firstname": "Marlyn",
    "lastname": "McCague",
    "username": "mmccague6"
  },
  {
    "uid": "c448f0ac-1da5-4d85-989f-62c77860109f",
    "firstname": "Shirlene",
    "lastname": "Minto",
    "username": "sminto7"
  },
  {
    "uid": "9efa58d0-5eb5-4680-bd5e-bdbb6841dece",
    "firstname": "Rubi",
    "lastname": "Buesnel",
    "username": "rbuesnel8"
  },
  {
    "uid": "38576361-ed28-4345-a64d-672d53f08490",
    "firstname": "Paolina",
    "lastname": "Dimsdale",
    "username": "pdimsdale9"
  },
  {
    "uid": "d4027728-47ce-4aad-b9f6-5b6c86301035",
    "firstname": "Reina",
    "lastname": "Aspall",
    "username": "raspalla"
  },
  {
    "uid": "3c992b28-ac04-4adb-a920-6447646ead5f",
    "firstname": "Sada",
    "lastname": "Elen",
    "username": "selenb"
  },
  {
    "uid": "afe7eb46-7e73-42d7-84e5-11fecddd4fdd",
    "firstname": "Packston",
    "lastname": "Dymidowicz",
    "username": "pdymidowiczc"
  },
  {
    "uid": "d375e085-6768-457e-b23d-5ad36c3fcb70",
    "firstname": "Meredeth",
    "lastname": "L'Archer",
    "username": "mlarcherd"
  },
  {
    "uid": "ccc56441-2b40-4cb2-b5b4-8989acbbaf31",
    "firstname": "Nananne",
    "lastname": "Kindred",
    "username": "nkindrede"
  },
  {
    "uid": "a0da6b1d-4c4a-44d6-ac04-0b8eddeb5015",
    "firstname": "Powell",
    "lastname": "Ingrey",
    "username": "pingreyf"
  },
  {
    "uid": "788bd6a4-92fa-4e05-a238-a79a294c07fd",
    "firstname": "Dynah",
    "lastname": "Leyfield",
    "username": "dleyfieldg"
  },
  {
    "uid": "20c23a17-39a3-4e3f-b090-11f2cedddd68",
    "firstname": "Jody",
    "lastname": "Norquoy",
    "username": "jnorquoyh"
  },
  {
    "uid": "c9cc64ac-eef8-4aa3-9c54-ab5077f08ec0",
    "firstname": "Marianne",
    "lastname": "Downer",
    "username": "mdowneri"
  },
  {
    "uid": "4c710952-78b6-4d68-945f-a518c336abf1",
    "firstname": "Hercules",
    "lastname": "Scintsbury",
    "username": "hscintsburyj"
  }
]